{
    "sourceFile": "Frontend/Frontend/src/Pages/FullSack.jsx",
    "activeCommit": 0,
    "commits": [
        {
            "activePatchIndex": 9,
            "patches": [
                {
                    "date": 1735207915995,
                    "content": "Index: \n===================================================================\n--- \n+++ \n"
                },
                {
                    "date": 1735207940896,
                    "content": "Index: \n===================================================================\n--- \n+++ \n@@ -1,7 +1,12 @@\n import React from 'react'\r\n+import { TopNav } from '../Components/Navbar/TopNav'\r\n+import { BottomNav } from '../Components/Navbar/BottomNav'\r\n \r\n export const FullSack = () => {\r\n   return (\r\n-    <div>FullSack</div>\r\n+    <div>\r\n+      <TopNav />\r\n+      <BottomNav />\r\n+    </div>\r\n   )\r\n }\r\n"
                },
                {
                    "date": 1735211652977,
                    "content": "Index: \n===================================================================\n--- \n+++ \n@@ -1,12 +1,14 @@\n import React from 'react'\r\n import { TopNav } from '../Components/Navbar/TopNav'\r\n import { BottomNav } from '../Components/Navbar/BottomNav'\r\n+import { Header } from '../Components/CoursesPage/FULLSTACK/Header.JSX'\r\n \r\n export const FullSack = () => {\r\n   return (\r\n     <div>\r\n       <TopNav />\r\n       <BottomNav />\r\n+      <Header />\r\n     </div>\r\n   )\r\n }\r\n"
                },
                {
                    "date": 1735211707172,
                    "content": "Index: \n===================================================================\n--- \n+++ \n@@ -1,14 +1,15 @@\n import React from 'react'\r\n import { TopNav } from '../Components/Navbar/TopNav'\r\n import { BottomNav } from '../Components/Navbar/BottomNav'\r\n-import { Header } from '../Components/CoursesPage/FULLSTACK/Header.JSX'\r\n+import { Header } from '../Components/CoursesPage/PHPPAGE/Header'\r\n \r\n+\r\n export const FullSack = () => {\r\n   return (\r\n     <div>\r\n       <TopNav />\r\n       <BottomNav />\r\n-      <Header />\r\n+     <Header />\r\n     </div>\r\n   )\r\n }\r\n"
                },
                {
                    "date": 1735212021329,
                    "content": "Index: \n===================================================================\n--- \n+++ \n@@ -1,15 +1,17 @@\n import React from 'react'\r\n import { TopNav } from '../Components/Navbar/TopNav'\r\n import { BottomNav } from '../Components/Navbar/BottomNav'\r\n import { Header } from '../Components/CoursesPage/PHPPAGE/Header'\r\n+import { MainContent } from '../Components/CoursesPage/FULLSTACK/MainContent'\r\n \r\n \r\n export const FullSack = () => {\r\n   return (\r\n     <div>\r\n       <TopNav />\r\n       <BottomNav />\r\n      <Header />\r\n+     <MainContent />\r\n     </div>\r\n   )\r\n }\r\n"
                },
                {
                    "date": 1735212065805,
                    "content": "Index: \n===================================================================\n--- \n+++ \n@@ -11,7 +11,8 @@\n       <TopNav />\r\n       <BottomNav />\r\n      <Header />\r\n      <MainContent />\r\n+     \r\n     </div>\r\n   )\r\n }\r\n"
                },
                {
                    "date": 1735212073055,
                    "content": "Index: \n===================================================================\n--- \n+++ \n@@ -2,8 +2,9 @@\n import { TopNav } from '../Components/Navbar/TopNav'\r\n import { BottomNav } from '../Components/Navbar/BottomNav'\r\n import { Header } from '../Components/CoursesPage/PHPPAGE/Header'\r\n import { MainContent } from '../Components/CoursesPage/FULLSTACK/MainContent'\r\n+import Footer from '../Components/Footer/Footer'\r\n \r\n \r\n export const FullSack = () => {\r\n   return (\r\n@@ -11,8 +12,9 @@\n       <TopNav />\r\n       <BottomNav />\r\n      <Header />\r\n      <MainContent />\r\n+     <Footer />\r\n      \r\n     </div>\r\n   )\r\n }\r\n"
                },
                {
                    "date": 1735212629117,
                    "content": "Index: \n===================================================================\n--- \n+++ \n@@ -3,8 +3,9 @@\n import { BottomNav } from '../Components/Navbar/BottomNav'\r\n import { Header } from '../Components/CoursesPage/PHPPAGE/Header'\r\n import { MainContent } from '../Components/CoursesPage/FULLSTACK/MainContent'\r\n import Footer from '../Components/Footer/Footer'\r\n+import CareerOpportunities from '../Components/CareerOpertunities'\r\n \r\n \r\n export const FullSack = () => {\r\n   return (\r\n@@ -12,8 +13,9 @@\n       <TopNav />\r\n       <BottomNav />\r\n      <Header />\r\n      <MainContent />\r\n+     <CareerOpportunities />\r\n      <Footer />\r\n      \r\n     </div>\r\n   )\r\n"
                },
                {
                    "date": 1735277117806,
                    "content": "Index: \n===================================================================\n--- \n+++ \n@@ -0,0 +1,22 @@\n+import React from 'react'\r\n+import { TopNav } from '../Components/Navbar/TopNav'\r\n+import { BottomNav } from '../Components/Navbar/BottomNav'\r\n+import { Header } from '../Components/CoursesPage/PHPPAGE/Header'\r\n+import { MainContent } from '../Components/CoursesPage/FULLSTACK/MainContent'\r\n+import Footer from '../Components/Footer/Footer'\r\n+import CareerOpportunities from '../Components/CareerOpertunities'\r\n+\r\n+\r\n+export const FullSack = () => {\r\n+  return (\r\n+    <div>\r\n+      <TopNav />\r\n+      <BottomNav />\r\n+     <Header />\r\n+     <MainContent />\r\n+     <CareerOpportunities />\r\n+     <Footer />\r\n+     \r\n+    </div>\r\n+  )\r\n+}\r\n"
                },
                {
                    "date": 1736070319700,
                    "content": "Index: \n===================================================================\n--- \n+++ \n@@ -1,33 +1,12 @@\n import React from 'react'\r\n import { TopNav } from '../Components/Navbar/TopNav'\r\n import { BottomNav } from '../Components/Navbar/BottomNav'\r\n-import { Header } from '../Components/CoursesPage/PHPPAGE/Header'\r\n-import { MainContent } from '../Components/CoursesPage/FULLSTACK/MainContent'\r\n-import Footer from '../Components/Footer/Footer'\r\n-import CareerOpportunities from '../Components/CareerOpertunities'\r\n \r\n-\r\n-export const FullSack = () => {\r\n-  return (\r\n-    <div>\r\n-      <TopNav />\r\n-      <BottomNav />\r\n-     <Header />\r\n-     <MainContent />\r\n-     <CareerOpportunities />\r\n-     <Footer />\r\n-     \r\n-    </div>\r\n-  )\r\n-}\r\n-import React from 'react'\r\n-import { TopNav } from '../Components/Navbar/TopNav'\r\n-import { BottomNav } from '../Components/Navbar/BottomNav'\r\n-import { Header } from '../Components/CoursesPage/PHPPAGE/Header'\r\n import { MainContent } from '../Components/CoursesPage/FULLSTACK/MainContent'\r\n import Footer from '../Components/Footer/Footer'\r\n import CareerOpportunities from '../Components/CareerOpertunities'\r\n+import { Header } from '../Components/CoursesPage/FULLSTACK/Header.JSX'\r\n \r\n \r\n export const FullSack = () => {\r\n   return (\r\n"
                }
            ],
            "date": 1735207915995,
            "name": "Commit-0",
            "content": "import React from 'react'\r\n\r\nexport const FullSack = () => {\r\n  return (\r\n    <div>FullSack</div>\r\n  )\r\n}\r\n"
        }
    ]
}